CHANGES.txt
CREDITS.txt
README.txt
bootstrap.py
buildout.cfg
setup.py
src/megrok/__init__.py
src/megrok.yui.egg-info/PKG-INFO
src/megrok.yui.egg-info/SOURCES.txt
src/megrok.yui.egg-info/dependency_links.txt
src/megrok.yui.egg-info/entry_points.txt
src/megrok.yui.egg-info/namespace_packages.txt
src/megrok.yui.egg-info/not-zip-safe
src/megrok.yui.egg-info/requires.txt
src/megrok.yui.egg-info/top_level.txt
src/megrok/yui/__init__.py
src/megrok/yui/configure.zcml
src/megrok/yui/yui.py
src/megrok/yui/yui-build/animation/README
src/megrok/yui/yui-build/animation/animation-debug.js
src/megrok/yui/yui-build/animation/animation-min.js
src/megrok/yui/yui-build/animation/animation.js
src/megrok/yui/yui-build/assets/skins/sam/asc.gif
src/megrok/yui/yui-build/assets/skins/sam/autocomplete.css
src/megrok/yui/yui-build/assets/skins/sam/blankimage.png
src/megrok/yui/yui-build/assets/skins/sam/button.css
src/megrok/yui/yui-build/assets/skins/sam/calendar.css
src/megrok/yui/yui-build/assets/skins/sam/colorpicker.css
src/megrok/yui/yui-build/assets/skins/sam/container.css
src/megrok/yui/yui-build/assets/skins/sam/datatable.css
src/megrok/yui/yui-build/assets/skins/sam/desc.gif
src/megrok/yui/yui-build/assets/skins/sam/dt-arrow-dn.png
src/megrok/yui/yui-build/assets/skins/sam/dt-arrow-up.png
src/megrok/yui/yui-build/assets/skins/sam/editor-knob.gif
src/megrok/yui/yui-build/assets/skins/sam/editor-sprite-active.gif
src/megrok/yui/yui-build/assets/skins/sam/editor-sprite.gif
src/megrok/yui/yui-build/assets/skins/sam/editor.css
src/megrok/yui/yui-build/assets/skins/sam/header_background.png
src/megrok/yui/yui-build/assets/skins/sam/hue_bg.png
src/megrok/yui/yui-build/assets/skins/sam/imagecropper.css
src/megrok/yui/yui-build/assets/skins/sam/layout.css
src/megrok/yui/yui-build/assets/skins/sam/layout_sprite.png
src/megrok/yui/yui-build/assets/skins/sam/logger.css
src/megrok/yui/yui-build/assets/skins/sam/menu-button-arrow-disabled.png
src/megrok/yui/yui-build/assets/skins/sam/menu-button-arrow.png
src/megrok/yui/yui-build/assets/skins/sam/menu.css
src/megrok/yui/yui-build/assets/skins/sam/menubaritem_submenuindicator.png
src/megrok/yui/yui-build/assets/skins/sam/menubaritem_submenuindicator_disabled.png
src/megrok/yui/yui-build/assets/skins/sam/menuitem_checkbox.png
