Metadata-Version: 1.0
Name: megrok.yui
Version: 2.5.2.1
Summary: YUI library packaged as a Grok resource library.
Home-page: UNKNOWN
Author: Grok Team, YAHOO
Author-email: grok-dev@zope.org
License: BSD
Platform: UNKNOWN
Classifier: Programming Language :: Python
Classifier: Programming Language :: JavaScript
Classifier: Framework :: Zope3
Classifier: Topic :: Software Development :: Libraries :: Python Modules
